psql_plugin_artema/__init__.py
psql_plugin_artema/adapters/__init__.py
psql_plugin_artema/adapters/inbound/__init__.py
psql_plugin_artema/adapters/inbound/async_cli_connector.py
psql_plugin_artema/adapters/inbound/cli_connector.py
psql_plugin_artema/adapters/outbound/__init__.py
psql_plugin_artema/adapters/outbound/async_psql_port.py
psql_plugin_artema/adapters/outbound/psql_port.py
psql_plugin_artema/application/__init__.py
psql_plugin_artema/application/dtos.py
psql_plugin_artema/application/interfaces/__init__.py
psql_plugin_artema/application/interfaces/async_psql_port.py
psql_plugin_artema/application/interfaces/psql_port.py
psql_plugin_artema/application/schemas/__init__.py
psql_plugin_artema/application/schemas/psql_connector_service_schemas.py
psql_plugin_artema/application/services/__init__.py
psql_plugin_artema/application/services/async_connector_service.py
psql_plugin_artema/application/services/connector_service.py
psql_plugin_artema/domain/__init__.py
psql_plugin_artema/domain/entities.py
psql_plugin_artema-0.1.0.dist-info/METADATA
psql_plugin_artema-0.1.0.dist-info/WHEEL
psql_plugin_artema-0.1.0.dist-info/RECORD
